pass_commander/__init__.py
pass_commander/__main__.py
pass_commander/commander.py
pass_commander/config.py
pass_commander/main.py
pass_commander/navigator.py
pass_commander/radio.py
pass_commander/rotator.py
pass_commander/satellite.py
pass_commander/station.py
pass_commander/tracker.py
pass_commander/mock/__init__.py
pass_commander/mock/flowgraph.py
pass_commander/mock/rotator.py
pass_commander/mock/station.py
uniclogs_pass_commander-1.0.1.dist-info/licenses/LICENSE
uniclogs_pass_commander-1.0.1.dist-info/METADATA
uniclogs_pass_commander-1.0.1.dist-info/WHEEL
uniclogs_pass_commander-1.0.1.dist-info/entry_points.txt
uniclogs_pass_commander-1.0.1.dist-info/top_level.txt
uniclogs_pass_commander-1.0.1.dist-info/RECORD
