Metadata-Version: 2.4
Name: uniclogs-pass-commander
Version: 1.0.1
Summary: The controller for local UniClOGS functions.
License: GPL-3.0
Requires-Python: >=3.11
License-File: LICENSE
Requires-Dist: jeepney>=0.8.0
Requires-Dist: linuxfd>=1.5
Requires-Dist: pyserial>=3.5
Requires-Dist: requests>=2.32.0
Requires-Dist: rot2prog>=0.0.9
Requires-Dist: tomlkit>=0.13.2
Requires-Dist: sgp4>=2.23
Requires-Dist: skyfield>=1.51
Provides-Extra: dev
Requires-Dist: build>=1.2.2; extra == "dev"
Requires-Dist: mypy>=1.17.0; extra == "dev"
Requires-Dist: pytest>=9.0.0; extra == "dev"
Requires-Dist: types-requests>=2.25; extra == "dev"
Requires-Dist: responses>=0.25.6; extra == "dev"
Requires-Dist: ruff>=0.8.0; extra == "dev"
Requires-Dist: pytest-cov>=7.0.0; extra == "dev"
Requires-Dist: setuptools>=80; extra == "dev"
Requires-Dist: setuptools-scm>=9; extra == "dev"
Dynamic: license-file
